pyutils/__init__.py
pyutils/cli/__init__.py
pyutils/cli/show.py
pyutils/matplotlib/__init__.py
pyutils/matplotlib/cmaps.py
pyutils/matplotlib/layout.py
pyutils/matplotlib/plot2d.py
pyutils/matplotlib/plot3d.py
pyutils/opencv/__init__.py
pyutils/utils/__init__.py
pyutils/utils/_colorings.py
pyutils/utils/_exceptions.py
pyutils/utils/_path.py
pyutils/utils/_warnings.py
pyutils/utils/argparse_utils.py
pyutils/utils/color_utils.py
pyutils/utils/generic_utils.py
pyutils/utils/json_utils.py
pyutils/utils/monitor_utils.py
pyutils/utils/numpy_utils.py
pyutils/utils/print_utils.py
Py_Charmers-0.0.1.dist-info/LICENSE
Py_Charmers-0.0.1.dist-info/METADATA
Py_Charmers-0.0.1.dist-info/WHEEL
Py_Charmers-0.0.1.dist-info/entry_points.txt
Py_Charmers-0.0.1.dist-info/top_level.txt
Py_Charmers-0.0.1.dist-info/RECORD
