Metadata-Version: 2.1
Name: Py-Charmers
Version: 0.0.1
Summary: A collection of useful python programs.
Home-page: UNKNOWN
Author: Shuto Iwasaki
Author-email: cabernet.rock@gmail.com
License: MIT
Project-URL: Bug Reports, https://github.com/iwasakishuto/PythonUtils/issues
Project-URL: Source Code, https://github.com/iwasakishuto/PythonUtils
Project-URL: Say Thanks!, https://twitter.com/cabernet_rock
Platform: UNKNOWN
Classifier: Development Status :: 1 - Planning
Classifier: Environment :: Console
Classifier: Intended Audience :: Other Audience
Classifier: License :: OSI Approved :: MIT License
Classifier: Programming Language :: Python :: 3
Classifier: Programming Language :: Python :: 3.8
Classifier: Topic :: Software Development :: Libraries :: Python Modules
Requires-Python: >=3.8
Requires-Dist: matplotlib (>=3.3.0)
Requires-Dist: numpy (>=1.18.5)
Requires-Dist: numpy-stl (>=2.11.2)
Requires-Dist: scipy (>=1.4.1)
Provides-Extra: tests
Requires-Dist: pytest ; extra == 'tests'
